README.rst
setup.py
cravat_multiuser/__init__.py
cravat_multiuser/favicon.ico
cravat_multiuser/favicon.png
cravat_multiuser/logout.png
cravat_multiuser/pwchng.png
cravat_multiuser/sign-out.svg
cravat_multiuser/nocache/OC_LOGO_WHITE.svg
cravat_multiuser/nocache/cravat_multiuser.css
cravat_multiuser/nocache/cravat_multiuser.js
cravat_multiuser/nocache/cravat_multiuser_module.js
cravat_multiuser/nocache/login.html
cravat_multiuser/nocache/login.png
cravat_multiuser/nocache/logo.png
cravat_multiuser/nocache/oc.png
open_cravat_multiuser.egg-info/PKG-INFO
open_cravat_multiuser.egg-info/SOURCES.txt
open_cravat_multiuser.egg-info/dependency_links.txt
open_cravat_multiuser.egg-info/requires.txt
open_cravat_multiuser.egg-info/top_level.txt