Metadata-Version: 2.1
Name: open-cravat-multiuser
Version: 2.12.1
Summary: OpenCRAVAT Multiuser Addon
Home-page: http://www.opencravat.org
Author: Rick Kim, Kyle Moad, Mike Ryan, and Rachel Karchin
Author-email: rkim@insilico.us.com
Requires-Python: >=3.6
Requires-Dist: aiohttp_session
Requires-Dist: cryptography
Requires-Dist: open-cravat>=2.2.2
